isolateparser/__init__.py
isolateparser/commandline.py
isolateparser/datatools.py
isolateparser/tableformat.py
isolateparser/workflow.py
isolateparser/generate/__init__.py
isolateparser/generate/generate_basic_statistics.py
isolateparser/generate/generate_comparison_table.py
isolateparser/generate/generate_fasta.py
isolateparser/generate/generate_isolate_table.py
isolateparser/resultparser/__init__.py
isolateparser/resultparser/breseq_folder_parser.py
workflow.py-0.1.0.data/scripts/breseqparser
workflow.py-0.1.0.dist-info/LICENSE.md
workflow.py-0.1.0.dist-info/METADATA
workflow.py-0.1.0.dist-info/WHEEL
workflow.py-0.1.0.dist-info/top_level.txt
workflow.py-0.1.0.dist-info/RECORD
