Metadata-Version: 2.1
Name: workflow.py
Version: 0.1.0
Summary: A set of scripts to convert multiple breseq analyses together and highlight variabls of interest.
Home-page: https://github.com/cdeitrick/isolate_parsers
Author: chris deitrick
Author-email: chrisdeitrick1@gmail.com
License: MIT
Platform: UNKNOWN
Classifier: Programming Language :: Python :: 3
Classifier: License :: OSI Approved :: MIT License
Classifier: Operating System :: OS Independent
Provides: i
Provides: s
Provides: o
Provides: l
Provides: a
Provides: t
Provides: e
Provides: p
Provides: a
Provides: r
Provides: s
Provides: e
Provides: r
Requires-Dist: pandas (>=0.24.0)
Requires-Dist: loguru
Requires-Dist: xlrd
Provides-Extra: additional_support_for_parsing_files
Requires-Dist: beautifulsoup4 ; extra == 'additional_support_for_parsing_files'
Provides-Extra: to_run_tests
Requires-Dist: pytest ; extra == 'to_run_tests'
